mdt_parser.py
mdt_render.py
plain_render.py
mdt/__init__.py
mdt/mdt_parser.py
mdt/mdt_render.py
mdt/sample_theme_text.md
mdt/version.py
mdt/themes/theme_001.json
mdt/themes/theme_002.json
mdt/themes/theme_003.json
mdt_viewer-0.2.0.dist-info/AUTHORS
mdt_viewer-0.2.0.dist-info/LICENSE
mdt_viewer-0.2.0.dist-info/METADATA
mdt_viewer-0.2.0.dist-info/WHEEL
mdt_viewer-0.2.0.dist-info/entry_points.txt
mdt_viewer-0.2.0.dist-info/pbr.json
mdt_viewer-0.2.0.dist-info/top_level.txt
mdt_viewer-0.2.0.dist-info/RECORD
