Metadata-Version: 2.1
Name: mdt-viewer
Version: 0.2.0
Summary: Markdown visualizer for the terminal with interactive features
Home-page: https://github.com/robolab-pavia/mdt
Author: Tullio Facchinetti
Author-email: toolleeo@gmail.com
License: GPL-3
Platform: UNKNOWN
Classifier: Programming Language :: Python :: 3
Classifier: Operating System :: OS Independent
Requires-Dist: ansiwrap
Requires-Dist: Click
Requires-Dist: Mistletoe
Requires-Dist: prompt-toolkit
